{"packages":{"mongodb/mongodb":{"0.1.0":{"name":"mongodb/mongodb","description":"MongoDB CRUD interface for PHongo","keywords":[],"homepage":"","version":"0.1.0","version_normalized":"0.1.0.0","license":["BSD-2-Clause"],"authors":[{"name":"Hannes Magnusson","email":"bjori@mongodb.com"}],"source":{"type":"git","url":"https://github.com/mongodb/mongo-php-library.git","reference":"4e8c6c57319dd1e9d30c594e1d07e7f8826ac013"},"dist":{"type":"zip","url":"https://api.github.com/repos/mongodb/mongo-php-library/zipball/4e8c6c57319dd1e9d30c594e1d07e7f8826ac013","reference":"4e8c6c57319dd1e9d30c594e1d07e7f8826ac013","shasum":""},"type":"library","time":"2014-12-12T01:28:19+00:00","autoload":{"psr-4":{"MongoDB\\":"src/"}},"require":{"ext-phongo":">=0.1.2"},"require-dev":{"fzaninotto/faker":"~1.0"},"uid":292201},"0.2.0":{"name":"mongodb/mongodb","description":"MongoDB driver library","keywords":["database","persistence","mongodb","driver"],"homepage":"https://jira.mongodb.org/browse/PHPLIB","version":"0.2.0","version_normalized":"0.2.0.0","license":["Apache-2.0"],"authors":[{"name":"Jeremy Mikola","email":"jmikola@gmail.com"},{"name":"Hannes Magnusson","email":"bjori@mongodb.com"},{"name":"Derick Rethans","email":"github@derickrethans.nl"}],"source":{"type":"git","url":"https://github.com/mongodb/mongo-php-library.git","reference":"98e14e8dc9a0c35e864baf999dc12433e937accd"},"dist":{"type":"zip","url":"https://api.github.com/repos/mongodb/mongo-php-library/zipball/98e14e8dc9a0c35e864baf999dc12433e937accd","reference":"98e14e8dc9a0c35e864baf999dc12433e937accd","shasum":""},"type":"library","time":"2015-05-12T23:33:27+00:00","autoload":{"psr-4":{"MongoDB\\":"src/"}},"extra":{"branch-alias":{"dev-master":"0.2.x-dev"}},"require":{"ext-mongodb":">=0.6.0"},"uid":404726},"1.0.0":{"name":"mongodb/mongodb","description":"MongoDB driver library","keywords":["database","persistence","mongodb","driver"],"homepage":"https://jira.mongodb.org/browse/PHPLIB","version":"1.0.0","version_normalized":"1.0.0.0","license":["Apache-2.0"],"authors":[{"name":"Jeremy Mikola","email":"jmikola@gmail.com"},{"name":"Hannes Magnusson","email":"bjori@mongodb.com"},{"name":"Derick Rethans","email":"github@derickrethans.nl"}],"source":{"type":"git","url":"https://github.com/mongodb/mongo-php-library.git","reference":"851a560864281cbf91fe182aefed85bfc3395031"},"dist":{"type":"zip","url":"https://api.github.com/repos/mongodb/mongo-php-library/zipball/851a560864281cbf91fe182aefed85bfc3395031","reference":"851a560864281cbf91fe182aefed85bfc3395031","shasum":""},"type":"library","time":"2016-01-21T19:43:25+00:00","autoload":{"psr-4":{"MongoDB\\":"src/"},"files":["src/functions.php"]},"extra":{"branch-alias":{"dev-master":"1.0.x-dev"}},"require":{"php":">=5.4","ext-mongodb":"^1.1.0"},"uid":667345},"1.0.0-alpha1":{"name":"mongodb/mongodb","description":"MongoDB driver library","keywords":["database","persistence","mongodb","driver"],"homepage":"https://jira.mongodb.org/browse/PHPLIB","version":"1.0.0-alpha1","version_normalized":"1.0.0.0-alpha1","license":["Apache-2.0"],"authors":[{"name":"Jeremy Mikola","email":"jmikola@gmail.com"},{"name":"Hannes Magnusson","email":"bjori@mongodb.com"},{"name":"Derick Rethans","email":"github@derickrethans.nl"}],"source":{"type":"git","url":"https://github.com/mongodb/mongo-php-library.git","reference":"39cb5bf858b7989f16b4f1c960f08fb4349fa666"},"dist":{"type":"zip","url":"https://api.github.com/repos/mongodb/mongo-php-library/zipball/39cb5bf858b7989f16b4f1c960f08fb4349fa666","reference":"39cb5bf858b7989f16b4f1c960f08fb4349fa666","shasum":""},"type":"library","time":"2015-10-07T18:47:38+00:00","autoload":{"psr-4":{"MongoDB\\":"src/"},"files":["src/functions.php"]},"extra":{"branch-alias":{"dev-master":"0.3.x-dev"}},"require":{"php":">=5.4","ext-mongodb":"^1.0.0"},"uid":544323},"1.0.0-beta1":{"name":"mongodb/mongodb","description":"MongoDB driver library","keywords":["database","persistence","mongodb","driver"],"homepage":"https://jira.mongodb.org/browse/PHPLIB","version":"1.0.0-beta1","version_normalized":"1.0.0.0-beta1","license":["Apache-2.0"],"authors":[{"name":"Jeremy Mikola","email":"jmikola@gmail.com"},{"name":"Hannes Magnusson","email":"bjori@mongodb.com"},{"name":"Derick Rethans","email":"github@derickrethans.nl"}],"source":{"type":"git","url":"https://github.com/mongodb/mongo-php-library.git","reference":"34b74f852af43fc70f49308bfbd3555f91db593c"},"dist":{"type":"zip","url":"https://api.github.com/repos/mongodb/mongo-php-library/zipball/34b74f852af43fc70f49308bfbd3555f91db593c","reference":"34b74f852af43fc70f49308bfbd3555f91db593c","shasum":""},"type":"library","time":"2015-11-02T21:31:19+00:00","autoload":{"psr-4":{"MongoDB\\":"src/"},"files":["src/functions.php"]},"extra":{"branch-alias":{"dev-master":"0.3.x-dev"}},"require":{"php":">=5.4","ext-mongodb":"^1.0.0"},"uid":571483},"1.0.0-beta2":{"name":"mongodb/mongodb","description":"MongoDB driver library","keywords":["database","persistence","mongodb","driver"],"homepage":"https://jira.mongodb.org/browse/PHPLIB","version":"1.0.0-beta2","version_normalized":"1.0.0.0-beta2","license":["Apache-2.0"],"authors":[{"name":"Jeremy Mikola","email":"jmikola@gmail.com"},{"name":"Hannes Magnusson","email":"bjori@mongodb.com"},{"name":"Derick Rethans","email":"github@derickrethans.nl"}],"source":{"type":"git","url":"https://github.com/mongodb/mongo-php-library.git","reference":"e8177e87efe74437b812915887d416f5b68b4e30"},"dist":{"type":"zip","url":"https://api.github.com/repos/mongodb/mongo-php-library/zipball/e8177e87efe74437b812915887d416f5b68b4e30","reference":"e8177e87efe74437b812915887d416f5b68b4e30","shasum":""},"type":"library","time":"2015-12-28T19:40:56+00:00","autoload":{"psr-4":{"MongoDB\\":"src/"},"files":["src/functions.php"]},"extra":{"branch-alias":{"dev-master":"1.0.x-dev"}},"require":{"php":">=5.4","ext-mongodb":"^1.1.1"},"uid":637328},"1.0.1":{"name":"mongodb/mongodb","description":"MongoDB driver library","keywords":["database","persistence","mongodb","driver"],"homepage":"https://jira.mongodb.org/browse/PHPLIB","version":"1.0.1","version_normalized":"1.0.1.0","license":["Apache-2.0"],"authors":[{"name":"Jeremy Mikola","email":"jmikola@gmail.com"},{"name":"Hannes Magnusson","email":"bjori@mongodb.com"},{"name":"Derick Rethans","email":"github@derickrethans.nl"}],"source":{"type":"git","url":"https://github.com/mongodb/mongo-php-library.git","reference":"6093d68c06bebcc5361b9e49178725efd9182ed4"},"dist":{"type":"zip","url":"https://api.github.com/repos/mongodb/mongo-php-library/zipball/6093d68c06bebcc5361b9e49178725efd9182ed4","reference":"6093d68c06bebcc5361b9e49178725efd9182ed4","shasum":""},"type":"library","time":"2016-03-04T20:27:01+00:00","autoload":{"psr-4":{"MongoDB\\":"src/"},"files":["src/functions.php"]},"extra":{"branch-alias":{"dev-master":"1.0.x-dev"}},"require":{"php":">=5.4","ext-mongodb":"^1.1.0"},"uid":724435},"1.0.2":{"name":"mongodb/mongodb","description":"MongoDB driver library","keywords":["database","persistence","mongodb","driver"],"homepage":"https://jira.mongodb.org/browse/PHPLIB","version":"1.0.2","version_normalized":"1.0.2.0","license":["Apache-2.0"],"authors":[{"name":"Jeremy Mikola","email":"jmikola@gmail.com"},{"name":"Hannes Magnusson","email":"bjori@mongodb.com"},{"name":"Derick Rethans","email":"github@derickrethans.nl"}],"source":{"type":"git","url":"https://github.com/mongodb/mongo-php-library.git","reference":"faf8a1d86b5c10684ef91fa6c81475b0c7f95240"},"dist":{"type":"zip","url":"https://api.github.com/repos/mongodb/mongo-php-library/zipball/faf8a1d86b5c10684ef91fa6c81475b0c7f95240","reference":"faf8a1d86b5c10684ef91fa6c81475b0c7f95240","shasum":""},"type":"library","time":"2016-03-30T19:10:28+00:00","autoload":{"psr-4":{"MongoDB\\":"src/"},"files":["src/functions.php"]},"require":{"php":">=5.4","ext-mongodb":"^1.1.0"},"uid":757946},"1.0.3":{"name":"mongodb/mongodb","description":"MongoDB driver library","keywords":["database","persistence","mongodb","driver"],"homepage":"https://jira.mongodb.org/browse/PHPLIB","version":"1.0.3","version_normalized":"1.0.3.0","license":["Apache-2.0"],"authors":[{"name":"Jeremy Mikola","email":"jmikola@gmail.com"},{"name":"Hannes Magnusson","email":"bjori@mongodb.com"},{"name":"Derick Rethans","email":"github@derickrethans.nl"}],"source":{"type":"git","url":"https://github.com/mongodb/mongo-php-library.git","reference":"3c742f3ceffc4dc67fee02dc6ebfc2e7cb403b7c"},"dist":{"type":"zip","url":"https://api.github.com/repos/mongodb/mongo-php-library/zipball/3c742f3ceffc4dc67fee02dc6ebfc2e7cb403b7c","reference":"3c742f3ceffc4dc67fee02dc6ebfc2e7cb403b7c","shasum":""},"type":"library","time":"2016-09-23T19:38:29+00:00","autoload":{"psr-4":{"MongoDB\\":"src/"},"files":["src/functions.php"]},"require":{"php":">=5.4","ext-mongodb":"^1.1.0"},"uid":1007345},"1.0.4":{"name":"mongodb/mongodb","description":"MongoDB driver library","keywords":["database","persistence","mongodb","driver"],"homepage":"https://jira.mongodb.org/browse/PHPLIB","version":"1.0.4","version_normalized":"1.0.4.0","license":["Apache-2.0"],"authors":[{"name":"Jeremy Mikola","email":"jmikola@gmail.com"},{"name":"Hannes Magnusson","email":"bjori@mongodb.com"},{"name":"Derick Rethans","email":"github@derickrethans.nl"}],"source":{"type":"git","url":"https://github.com/mongodb/mongo-php-library.git","reference":"302de20d8302183e1c70b335d81798cec5bcebd4"},"dist":{"type":"zip","url":"https://api.github.com/repos/mongodb/mongo-php-library/zipball/302de20d8302183e1c70b335d81798cec5bcebd4","reference":"302de20d8302183e1c70b335d81798cec5bcebd4","shasum":""},"type":"library","time":"2016-12-05T20:02:14+00:00","autoload":{"psr-4":{"MongoDB\\":"src/"},"files":["src/functions.php"]},"require":{"php":">=5.4","ext-mongodb":"^1.1.0"},"uid":1113450},"1.0.5":{"name":"mongodb/mongodb","description":"MongoDB driver library","keywords":["database","persistence","mongodb","driver"],"homepage":"https://jira.mongodb.org/browse/PHPLIB","version":"1.0.5","version_normalized":"1.0.5.0","license":["Apache-2.0"],"authors":[{"name":"Jeremy Mikola","email":"jmikola@gmail.com"},{"name":"Hannes Magnusson","email":"bjori@mongodb.com"},{"name":"Derick Rethans","email":"github@derickrethans.nl"}],"source":{"type":"git","url":"https://github.com/mongodb/mongo-php-library.git","reference":"2f99156b29bc85582415d6a32bc31010d61a0a71"},"dist":{"type":"zip","url":"https://api.github.com/repos/mongodb/mongo-php-library/zipball/2f99156b29bc85582415d6a32bc31010d61a0a71","reference":"2f99156b29bc85582415d6a32bc31010d61a0a71","shasum":""},"type":"library","time":"2017-02-16T18:35:09+00:00","autoload":{"psr-4":{"MongoDB\\":"src/"},"files":["src/functions.php"]},"require":{"php":">=5.4","ext-mongodb":"^1.1.0"},"uid":1236557},"1.1.0":{"name":"mongodb/mongodb","description":"MongoDB driver library","keywords":["database","persistence","mongodb","driver"],"homepage":"https://jira.mongodb.org/browse/PHPLIB","version":"1.1.0","version_normalized":"1.1.0.0","license":["Apache-2.0"],"authors":[{"name":"Jeremy Mikola","email":"jmikola@gmail.com"},{"name":"Hannes Magnusson","email":"bjori@mongodb.com"},{"name":"Derick Rethans","email":"github@derickrethans.nl"}],"source":{"type":"git","url":"https://github.com/mongodb/mongo-php-library.git","reference":"9dfb2c5fc917d7438b44eb8f4d247ba3e3984e75"},"dist":{"type":"zip","url":"https://api.github.com/repos/mongodb/mongo-php-library/zipball/9dfb2c5fc917d7438b44eb8f4d247ba3e3984e75","reference":"9dfb2c5fc917d7438b44eb8f4d247ba3e3984e75","shasum":""},"type":"library","time":"2016-12-06T14:54:33+00:00","autoload":{"psr-4":{"MongoDB\\":"src/"},"files":["src/functions.php"]},"extra":{"branch-alias":{"dev-master":"1.1.x-dev"}},"require":{"php":">=5.4","ext-mongodb":"^1.2.0"},"require-dev":{"phpunit/phpunit":"^4.8"},"uid":1114842},"1.1.0-alpha1":{"name":"mongodb/mongodb","description":"MongoDB driver library","keywords":["database","persistence","mongodb","driver"],"homepage":"https://jira.mongodb.org/browse/PHPLIB","version":"1.1.0-alpha1","version_normalized":"1.1.0.0-alpha1","license":["Apache-2.0"],"authors":[{"name":"Jeremy Mikola","email":"jmikola@gmail.com"},{"name":"Hannes Magnusson","email":"bjori@mongodb.com"},{"name":"Derick Rethans","email":"github@derickrethans.nl"}],"source":{"type":"git","url":"https://github.com/mongodb/mongo-php-library.git","reference":"55e2a31d92a1ad6740dbf251d3e7b1ac07c503a3"},"dist":{"type":"zip","url":"https://api.github.com/repos/mongodb/mongo-php-library/zipball/55e2a31d92a1ad6740dbf251d3e7b1ac07c503a3","reference":"55e2a31d92a1ad6740dbf251d3e7b1ac07c503a3","shasum":""},"type":"library","time":"2016-09-28T22:45:39+00:00","autoload":{"psr-4":{"MongoDB\\":"src/"},"files":["src/functions.php"]},"extra":{"branch-alias":{"dev-master":"1.1.x-dev"}},"require":{"php":">=5.4","ext-mongodb":"^1.1.0"},"require-dev":{"phpunit/phpunit":"^4.8"},"uid":1014906},"1.1.1":{"name":"mongodb/mongodb","description":"MongoDB driver library","keywords":["database","persistence","mongodb","driver"],"homepage":"https://jira.mongodb.org/browse/PHPLIB","version":"1.1.1","version_normalized":"1.1.1.0","license":["Apache-2.0"],"authors":[{"name":"Jeremy Mikola","email":"jmikola@gmail.com"},{"name":"Hannes Magnusson","email":"bjori@mongodb.com"},{"name":"Derick Rethans","email":"github@derickrethans.nl"}],"source":{"type":"git","url":"https://github.com/mongodb/mongo-php-library.git","reference":"318d4b95438a2ea68a550c2878678097f63fb9fe"},"dist":{"type":"zip","url":"https://api.github.com/repos/mongodb/mongo-php-library/zipball/318d4b95438a2ea68a550c2878678097f63fb9fe","reference":"318d4b95438a2ea68a550c2878678097f63fb9fe","shasum":""},"type":"library","time":"2017-01-17T19:59:32+00:00","autoload":{"psr-4":{"MongoDB\\":"src/"},"files":["src/functions.php"]},"extra":{"branch-alias":{"dev-master":"1.1.x-dev"}},"require":{"php":">=5.4","ext-mongodb":"^1.2.0"},"require-dev":{"phpunit/phpunit":"^4.8"},"uid":1181340},"1.1.2":{"name":"mongodb/mongodb","description":"MongoDB driver library","keywords":["database","persistence","mongodb","driver"],"homepage":"https://jira.mongodb.org/browse/PHPLIB","version":"1.1.2","version_normalized":"1.1.2.0","license":["Apache-2.0"],"authors":[{"name":"Jeremy Mikola","email":"jmikola@gmail.com"},{"name":"Hannes Magnusson","email":"bjori@mongodb.com"},{"name":"Derick Rethans","email":"github@derickrethans.nl"}],"source":{"type":"git","url":"https://github.com/mongodb/mongo-php-library.git","reference":"a307dd60e71e1291c60927ea4f3a1905146063f5"},"dist":{"type":"zip","url":"https://api.github.com/repos/mongodb/mongo-php-library/zipball/a307dd60e71e1291c60927ea4f3a1905146063f5","reference":"a307dd60e71e1291c60927ea4f3a1905146063f5","shasum":""},"type":"library","time":"2017-02-16T18:40:32+00:00","autoload":{"psr-4":{"MongoDB\\":"src/"},"files":["src/functions.php"]},"require":{"php":">=5.4","ext-mongodb":"^1.2.0"},"require-dev":{"phpunit/phpunit":"^4.8"},"uid":1236568},"1.2.0":{"name":"mongodb/mongodb","description":"MongoDB driver library","keywords":["database","persistence","mongodb","driver"],"homepage":"https://jira.mongodb.org/browse/PHPLIB","version":"1.2.0","version_normalized":"1.2.0.0","license":["Apache-2.0"],"authors":[{"name":"Jeremy Mikola","email":"jmikola@gmail.com"},{"name":"Hannes Magnusson","email":"bjori@mongodb.com"},{"name":"Derick Rethans","email":"github@derickrethans.nl"}],"source":{"type":"git","url":"https://github.com/mongodb/mongo-php-library.git","reference":"5cffeb33b893b6bb04195b99ddc3955a29252339"},"dist":{"type":"zip","url":"https://api.github.com/repos/mongodb/mongo-php-library/zipball/5cffeb33b893b6bb04195b99ddc3955a29252339","reference":"5cffeb33b893b6bb04195b99ddc3955a29252339","shasum":""},"type":"library","time":"2017-10-27T19:42:57+00:00","autoload":{"psr-4":{"MongoDB\\":"src/"},"files":["src/functions.php"]},"require":{"php":">=5.5","ext-hash":"*","ext-json":"*","ext-mongodb":"^1.3.0"},"require-dev":{"phpunit/phpunit":"^4.8"},"uid":1695121},"1.2.0-alpha1":{"name":"mongodb/mongodb","description":"MongoDB driver library","keywords":["database","persistence","mongodb","driver"],"homepage":"https://jira.mongodb.org/browse/PHPLIB","version":"1.2.0-alpha1","version_normalized":"1.2.0.0-alpha1","license":["Apache-2.0"],"authors":[{"name":"Jeremy Mikola","email":"jmikola@gmail.com"},{"name":"Hannes Magnusson","email":"bjori@mongodb.com"},{"name":"Derick Rethans","email":"github@derickrethans.nl"}],"source":{"type":"git","url":"https://github.com/mongodb/mongo-php-library.git","reference":"ed578ab2f3e50078e344cea82203dad731d9edb3"},"dist":{"type":"zip","url":"https://api.github.com/repos/mongodb/mongo-php-library/zipball/ed578ab2f3e50078e344cea82203dad731d9edb3","reference":"ed578ab2f3e50078e344cea82203dad731d9edb3","shasum":""},"type":"library","time":"2017-03-16T17:22:35+00:00","autoload":{"psr-4":{"MongoDB\\":"src/"},"files":["src/functions.php"]},"extra":{"branch-alias":{"dev-master":"1.2.x-dev"}},"require":{"php":">=5.4","ext-mongodb":"^1.2.0"},"require-dev":{"phpunit/phpunit":"^4.8"},"uid":1289840},"1.3.0":{"name":"mongodb/mongodb","description":"MongoDB driver library","keywords":["database","persistence","mongodb","driver"],"homepage":"https://jira.mongodb.org/browse/PHPLIB","version":"1.3.0","version_normalized":"1.3.0.0","license":["Apache-2.0"],"authors":[{"name":"Jeremy Mikola","email":"jmikola@gmail.com"},{"name":"Derick Rethans","email":"github@derickrethans.nl"},{"name":"Katherine Walker","email":"katherine.walker@mongodb.com"}],"source":{"type":"git","url":"https://github.com/mongodb/mongo-php-library.git","reference":"07ffd2438658342b776803323cfaa7c156a6099a"},"dist":{"type":"zip","url":"https://api.github.com/repos/mongodb/mongo-php-library/zipball/07ffd2438658342b776803323cfaa7c156a6099a","reference":"07ffd2438658342b776803323cfaa7c156a6099a","shasum":""},"type":"library","time":"2018-02-08T16:30:23+00:00","autoload":{"psr-4":{"MongoDB\\":"src/"},"files":["src/functions.php"]},"extra":{"branch-alias":{"dev-master":"1.3.x-dev"}},"require":{"php":">=5.5","ext-hash":"*","ext-json":"*","ext-mongodb":"^1.4.0"},"require-dev":{"phpunit/phpunit":"^4.8.36"},"uid":1902659},"1.3.1":{"name":"mongodb/mongodb","description":"MongoDB driver library","keywords":["database","persistence","mongodb","driver"],"homepage":"https://jira.mongodb.org/browse/PHPLIB","version":"1.3.1","version_normalized":"1.3.1.0","license":["Apache-2.0"],"authors":[{"name":"Jeremy Mikola","email":"jmikola@gmail.com"},{"name":"Derick Rethans","email":"github@derickrethans.nl"},{"name":"Katherine Walker","email":"katherine.walker@mongodb.com"}],"source":{"type":"git","url":"https://github.com/mongodb/mongo-php-library.git","reference":"7417ecf1ca5aef263d3e2fdc4ace214f7fd1b750"},"dist":{"type":"zip","url":"https://api.github.com/repos/mongodb/mongo-php-library/zipball/7417ecf1ca5aef263d3e2fdc4ace214f7fd1b750","reference":"7417ecf1ca5aef263d3e2fdc4ace214f7fd1b750","shasum":""},"type":"library","time":"2018-03-19T18:40:25+00:00","autoload":{"psr-4":{"MongoDB\\":"src/"},"files":["src/functions.php"]},"extra":{"branch-alias":{"dev-master":"1.3.x-dev"}},"require":{"php":">=5.5","ext-hash":"*","ext-json":"*","ext-mongodb":"^1.4.0"},"require-dev":{"phpunit/phpunit":"^4.8.36 || ^6.4"},"uid":2038054},"1.3.2":{"name":"mongodb/mongodb","description":"MongoDB driver library","keywords":["database","persistence","mongodb","driver"],"homepage":"https://jira.mongodb.org/browse/PHPLIB","version":"1.3.2","version_normalized":"1.3.2.0","license":["Apache-2.0"],"authors":[{"name":"Jeremy Mikola","email":"jmikola@gmail.com"},{"name":"Derick Rethans","email":"github@derickrethans.nl"},{"name":"Katherine Walker","email":"katherine.walker@mongodb.com"}],"source":{"type":"git","url":"https://github.com/mongodb/mongo-php-library.git","reference":"b9f35916125976533f4b1e67a4a0ee7baf1d3bb9"},"dist":{"type":"zip","url":"https://api.github.com/repos/mongodb/mongo-php-library/zipball/b9f35916125976533f4b1e67a4a0ee7baf1d3bb9","reference":"b9f35916125976533f4b1e67a4a0ee7baf1d3bb9","shasum":""},"type":"library","time":"2018-04-19T17:20:30+00:00","autoload":{"psr-4":{"MongoDB\\":"src/"},"files":["src/functions.php"]},"extra":{"branch-alias":{"dev-master":"1.3.x-dev"}},"require":{"php":">=5.5","ext-hash":"*","ext-json":"*","ext-mongodb":"^1.4.0"},"require-dev":{"phpunit/phpunit":"^4.8.36 || ^6.4"},"uid":2113366},"1.4.0":{"name":"mongodb/mongodb","description":"MongoDB driver library","keywords":["database","persistence","mongodb","driver"],"homepage":"https://jira.mongodb.org/browse/PHPLIB","version":"1.4.0","version_normalized":"1.4.0.0","license":["Apache-2.0"],"authors":[{"name":"Jeremy Mikola","email":"jmikola@gmail.com"},{"name":"Derick Rethans","email":"github@derickrethans.nl"},{"name":"Katherine Walker","email":"katherine.walker@mongodb.com"}],"source":{"type":"git","url":"https://github.com/mongodb/mongo-php-library.git","reference":"ae05e905dbb3ae5fac846a2906dd273d717708f2"},"dist":{"type":"zip","url":"https://api.github.com/repos/mongodb/mongo-php-library/zipball/ae05e905dbb3ae5fac846a2906dd273d717708f2","reference":"ae05e905dbb3ae5fac846a2906dd273d717708f2","shasum":""},"type":"library","time":"2018-06-27T17:05:43+00:00","autoload":{"psr-4":{"MongoDB\\":"src/"},"files":["src/functions.php"]},"extra":{"branch-alias":{"dev-master":"1.3.x-dev"}},"require":{"php":">=5.5","ext-hash":"*","ext-json":"*","ext-mongodb":"^1.5.0"},"require-dev":{"phpunit/phpunit":"^4.8.36 || ^6.4"},"uid":2293881},"1.4.1":{"name":"mongodb/mongodb","description":"MongoDB driver library","keywords":["database","persistence","mongodb","driver"],"homepage":"https://jira.mongodb.org/browse/PHPLIB","version":"1.4.1","version_normalized":"1.4.1.0","license":["Apache-2.0"],"authors":[{"name":"Jeremy Mikola","email":"jmikola@gmail.com"},{"name":"Derick Rethans","email":"github@derickrethans.nl"},{"name":"Katherine Walker","email":"katherine.walker@mongodb.com"}],"source":{"type":"git","url":"https://github.com/mongodb/mongo-php-library.git","reference":"0534ed0ff44e26fe96e9172e7f34e2bbf5c0efde"},"dist":{"type":"zip","url":"https://api.github.com/repos/mongodb/mongo-php-library/zipball/0534ed0ff44e26fe96e9172e7f34e2bbf5c0efde","reference":"0534ed0ff44e26fe96e9172e7f34e2bbf5c0efde","shasum":""},"type":"library","time":"2018-07-10T15:23:29+00:00","autoload":{"psr-4":{"MongoDB\\":"src/"},"files":["src/functions.php"]},"extra":{"branch-alias":{"dev-master":"1.4.x-dev"}},"require":{"php":">=5.5","ext-hash":"*","ext-json":"*","ext-mongodb":"^1.5.0"},"require-dev":{"phpunit/phpunit":"^4.8.36 || ^6.4"},"uid":2322612},"1.4.2":{"name":"mongodb/mongodb","description":"MongoDB driver library","keywords":["database","persistence","mongodb","driver"],"homepage":"https://jira.mongodb.org/browse/PHPLIB","version":"1.4.2","version_normalized":"1.4.2.0","license":["Apache-2.0"],"authors":[{"name":"Jeremy Mikola","email":"jmikola@gmail.com"},{"name":"Derick Rethans","email":"github@derickrethans.nl"},{"name":"Katherine Walker","email":"katherine.walker@mongodb.com"}],"source":{"type":"git","url":"https://github.com/mongodb/mongo-php-library.git","reference":"bd148eab0493e38354e45e2cd7db59b90fdcad79"},"dist":{"type":"zip","url":"https://api.github.com/repos/mongodb/mongo-php-library/zipball/bd148eab0493e38354e45e2cd7db59b90fdcad79","reference":"bd148eab0493e38354e45e2cd7db59b90fdcad79","shasum":""},"type":"library","time":"2018-07-18T14:33:41+00:00","autoload":{"psr-4":{"MongoDB\\":"src/"},"files":["src/functions.php"]},"extra":{"branch-alias":{"dev-master":"1.4.x-dev"}},"require":{"php":">=5.5","ext-hash":"*","ext-json":"*","ext-mongodb":"^1.5.0"},"require-dev":{"phpunit/phpunit":"^4.8.36 || ^6.4"},"uid":2369070},"1.4.3":{"name":"mongodb/mongodb","description":"MongoDB driver library","keywords":["database","persistence","mongodb","driver"],"homepage":"https://jira.mongodb.org/browse/PHPLIB","version":"1.4.3","version_normalized":"1.4.3.0","license":["Apache-2.0"],"authors":[{"name":"Jeremy Mikola","email":"jmikola@gmail.com"},{"name":"Derick Rethans","email":"github@derickrethans.nl"},{"name":"Katherine Walker","email":"katherine.walker@mongodb.com"}],"source":{"type":"git","url":"https://github.com/mongodb/mongo-php-library.git","reference":"18fca8cc8d0c2cc07f76605760d20632bb3dab96"},"dist":{"type":"zip","url":"https://api.github.com/repos/mongodb/mongo-php-library/zipball/18fca8cc8d0c2cc07f76605760d20632bb3dab96","reference":"18fca8cc8d0c2cc07f76605760d20632bb3dab96","shasum":""},"type":"library","time":"2019-07-02T18:04:14+00:00","autoload":{"psr-4":{"MongoDB\\":"src/"},"files":["src/functions.php"]},"require":{"php":">=5.5","ext-hash":"*","ext-json":"*","ext-mongodb":"^1.5.0"},"require-dev":{"phpunit/phpunit":"^4.8.36 || ^6.4"},"uid":3105540},"1.5.0":{"name":"mongodb/mongodb","description":"MongoDB driver library","keywords":["database","persistence","mongodb","driver"],"homepage":"https://jira.mongodb.org/browse/PHPLIB","version":"1.5.0","version_normalized":"1.5.0.0","license":["Apache-2.0"],"authors":[{"name":"Andreas Braun","email":"andreas.braun@mongodb.com"},{"name":"Jeremy Mikola","email":"jmikola@gmail.com"},{"name":"Katherine Walker","email":"katherine.walker@mongodb.com"}],"source":{"type":"git","url":"https://github.com/mongodb/mongo-php-library.git","reference":"6405e91ba63955bcd187d3bab9ec7327d17cc4ce"},"dist":{"type":"zip","url":"https://api.github.com/repos/mongodb/mongo-php-library/zipball/6405e91ba63955bcd187d3bab9ec7327d17cc4ce","reference":"6405e91ba63955bcd187d3bab9ec7327d17cc4ce","shasum":""},"type":"library","time":"2019-09-09T13:42:06+00:00","autoload":{"psr-4":{"MongoDB\\":"src/"},"files":["src/functions.php"]},"extra":{"branch-alias":{"dev-master":"1.5.x-dev"}},"require":{"php":"^5.6 || ^7.0","ext-hash":"*","ext-json":"*","ext-mongodb":"^1.6"},"require-dev":{"phpunit/phpunit":"^5.7.27 || ^6.4 || ^8.3","sebastian/comparator":"^1.0 || ^2.0 || ^3.0","squizlabs/php_codesniffer":"^3.4","symfony/phpunit-bridge":"^4.4@dev"},"uid":3221933},"1.5.1":{"name":"mongodb/mongodb","description":"MongoDB driver library","keywords":["database","persistence","mongodb","driver"],"homepage":"https://jira.mongodb.org/browse/PHPLIB","version":"1.5.1","version_normalized":"1.5.1.0","license":["Apache-2.0"],"authors":[{"name":"Andreas Braun","email":"andreas.braun@mongodb.com"},{"name":"Jeremy Mikola","email":"jmikola@gmail.com"},{"name":"Katherine Walker","email":"katherine.walker@mongodb.com"}],"source":{"type":"git","url":"https://github.com/mongodb/mongo-php-library.git","reference":"32cfb9bbd0bc60a5a13ca9eab7e4803226a5d4a7"},"dist":{"type":"zip","url":"https://api.github.com/repos/mongodb/mongo-php-library/zipball/32cfb9bbd0bc60a5a13ca9eab7e4803226a5d4a7","reference":"32cfb9bbd0bc60a5a13ca9eab7e4803226a5d4a7","shasum":""},"type":"library","time":"2019-10-09T14:34:41+00:00","autoload":{"psr-4":{"MongoDB\\":"src/"},"files":["src/functions.php"]},"extra":{"branch-alias":{"dev-master":"1.5.x-dev"}},"require":{"php":"^5.6 || ^7.0","ext-hash":"*","ext-json":"*","ext-mongodb":"^1.6"},"require-dev":{"phpunit/phpunit":"^5.7.27 || ^6.4 || ^8.3","sebastian/comparator":"^1.0 || ^2.0 || ^3.0","squizlabs/php_codesniffer":"^3.4","symfony/phpunit-bridge":"^4.4@dev"},"uid":3336262},"1.5.2":{"name":"mongodb/mongodb","description":"MongoDB driver library","keywords":["database","persistence","mongodb","driver"],"homepage":"https://jira.mongodb.org/browse/PHPLIB","version":"1.5.2","version_normalized":"1.5.2.0","license":["Apache-2.0"],"authors":[{"name":"Andreas Braun","email":"andreas.braun@mongodb.com"},{"name":"Jeremy Mikola","email":"jmikola@gmail.com"},{"name":"Katherine Walker","email":"katherine.walker@mongodb.com"}],"source":{"type":"git","url":"https://github.com/mongodb/mongo-php-library.git","reference":"9480f994de9f70e2ae5a946b21e6fc04bf5a6c3c"},"dist":{"type":"zip","url":"https://api.github.com/repos/mongodb/mongo-php-library/zipball/9480f994de9f70e2ae5a946b21e6fc04bf5a6c3c","reference":"9480f994de9f70e2ae5a946b21e6fc04bf5a6c3c","shasum":""},"type":"library","time":"2019-11-15T08:21:00+00:00","autoload":{"psr-4":{"MongoDB\\":"src/"},"files":["src/functions.php"]},"extra":{"branch-alias":{"dev-master":"1.5.x-dev"}},"require":{"php":"^5.6 || ^7.0","ext-hash":"*","ext-json":"*","ext-mongodb":"^1.6"},"require-dev":{"phpunit/phpunit":"^5.7.27 || ^6.4 || ^8.3","sebastian/comparator":"^1.0 || ^2.0 || ^3.0","squizlabs/php_codesniffer":"^3.4","symfony/phpunit-bridge":"^4.4@dev"},"uid":3533236},"1.6.0":{"name":"mongodb/mongodb","description":"MongoDB driver library","keywords":["database","persistence","mongodb","driver"],"homepage":"https://jira.mongodb.org/browse/PHPLIB","version":"1.6.0","version_normalized":"1.6.0.0","license":["Apache-2.0"],"authors":[{"name":"Andreas Braun","email":"andreas.braun@mongodb.com"},{"name":"Jeremy Mikola","email":"jmikola@gmail.com"},{"name":"Katherine Walker","email":"katherine.walker@mongodb.com"}],"source":{"type":"git","url":"https://github.com/mongodb/mongo-php-library.git","reference":"dc43ba25fb593d6a2988e6a535b6f5386eda5b15"},"dist":{"type":"zip","url":"https://api.github.com/repos/mongodb/mongo-php-library/zipball/dc43ba25fb593d6a2988e6a535b6f5386eda5b15","reference":"dc43ba25fb593d6a2988e6a535b6f5386eda5b15","shasum":""},"type":"library","time":"2020-02-04T18:16:35+00:00","autoload":{"psr-4":{"MongoDB\\":"src/"},"files":["src/functions.php"]},"extra":{"branch-alias":{"dev-master":"1.6.x-dev"}},"require":{"php":"^5.6 || ^7.0","ext-hash":"*","ext-json":"*","ext-mongodb":"^1.7"},"require-dev":{"phpunit/phpunit":"^5.7.27 || ^6.4 || ^8.3","sebastian/comparator":"^1.0 || ^2.0 || ^3.0","squizlabs/php_codesniffer":"^3.4","symfony/phpunit-bridge":"^4.4@dev"},"uid":3586091},"1.6.1":{"name":"mongodb/mongodb","description":"MongoDB driver library","keywords":["database","persistence","mongodb","driver"],"homepage":"https://jira.mongodb.org/browse/PHPLIB","version":"1.6.1","version_normalized":"1.6.1.0","license":["Apache-2.0"],"authors":[{"name":"Andreas Braun","email":"andreas.braun@mongodb.com"},{"name":"Jeremy Mikola","email":"jmikola@gmail.com"},{"name":"Katherine Walker","email":"katherine.walker@mongodb.com"}],"source":{"type":"git","url":"https://github.com/mongodb/mongo-php-library.git","reference":"4bb040c620ab95c487d05d5ff50cbc92fa68e920"},"dist":{"type":"zip","url":"https://api.github.com/repos/mongodb/mongo-php-library/zipball/4bb040c620ab95c487d05d5ff50cbc92fa68e920","reference":"4bb040c620ab95c487d05d5ff50cbc92fa68e920","shasum":""},"type":"library","time":"2020-07-03T11:35:00+00:00","autoload":{"psr-4":{"MongoDB\\":"src/"},"files":["src/functions.php"]},"extra":{"branch-alias":{"dev-master":"1.6.x-dev"}},"require":{"php":"^5.6 || ^7.0","ext-hash":"*","ext-json":"*","ext-mongodb":"^1.7"},"require-dev":{"phpunit/phpunit":"^5.7.27 || ^6.4 || ^8.3","sebastian/comparator":"^1.0 || ^2.0 || ^3.0","squizlabs/php_codesniffer":"^3.4","symfony/phpunit-bridge":"^4.4@dev"},"uid":4201325},"1.7.0":{"name":"mongodb/mongodb","description":"MongoDB driver library","keywords":["database","persistence","mongodb","driver"],"homepage":"https://jira.mongodb.org/browse/PHPLIB","version":"1.7.0","version_normalized":"1.7.0.0","license":["Apache-2.0"],"authors":[{"name":"Andreas Braun","email":"andreas.braun@mongodb.com"},{"name":"Jeremy Mikola","email":"jmikola@gmail.com"}],"source":{"type":"git","url":"https://github.com/mongodb/mongo-php-library.git","reference":"cdeff1d45e4da6c6f70fc495e8e8a628b026b6d7"},"dist":{"type":"zip","url":"https://api.github.com/repos/mongodb/mongo-php-library/zipball/cdeff1d45e4da6c6f70fc495e8e8a628b026b6d7","reference":"cdeff1d45e4da6c6f70fc495e8e8a628b026b6d7","shasum":""},"type":"library","time":"2020-07-31T19:48:22+00:00","autoload":{"psr-4":{"MongoDB\\":"src/"},"files":["src/functions.php"]},"extra":{"branch-alias":{"dev-master":"1.7.x-dev"}},"require":{"php":"^7.0","ext-hash":"*","ext-json":"*","ext-mongodb":"^1.8","jean85/pretty-package-versions":"^1.2"},"require-dev":{"phpunit/phpunit":"^6.4 || ^8.3","sebastian/comparator":"^2.0 || ^3.0","squizlabs/php_codesniffer":"^3.5, <3.5.5","symfony/phpunit-bridge":"^4.4@dev"},"uid":4320628},"1.7.0-beta1":{"name":"mongodb/mongodb","description":"MongoDB driver library","keywords":["database","persistence","mongodb","driver"],"homepage":"https://jira.mongodb.org/browse/PHPLIB","version":"1.7.0-beta1","version_normalized":"1.7.0.0-beta1","license":["Apache-2.0"],"authors":[{"name":"Andreas Braun","email":"andreas.braun@mongodb.com"},{"name":"Jeremy Mikola","email":"jmikola@gmail.com"},{"name":"Katherine Walker","email":"katherine.walker@mongodb.com"}],"source":{"type":"git","url":"https://github.com/mongodb/mongo-php-library.git","reference":"5e802f03b02c3f2a10a3e4c1bae0de7ad13fc02a"},"dist":{"type":"zip","url":"https://api.github.com/repos/mongodb/mongo-php-library/zipball/5e802f03b02c3f2a10a3e4c1bae0de7ad13fc02a","reference":"5e802f03b02c3f2a10a3e4c1bae0de7ad13fc02a","shasum":""},"type":"library","time":"2020-04-14T10:08:16+00:00","autoload":{"psr-4":{"MongoDB\\":"src/"},"files":["src/functions.php"]},"extra":{"branch-alias":{"dev-master":"1.7.x-dev"}},"require":{"php":"^7.0","ext-hash":"*","ext-json":"*","ext-mongodb":"^1.8","jean85/pretty-package-versions":"^1.2"},"require-dev":{"phpunit/phpunit":"^6.4 || ^8.3","sebastian/comparator":"^2.0 || ^3.0","squizlabs/php_codesniffer":"^3.5","symfony/phpunit-bridge":"^4.4@dev"},"uid":3781874},"1.7.0-beta2":{"name":"mongodb/mongodb","description":"MongoDB driver library","keywords":["database","persistence","mongodb","driver"],"homepage":"https://jira.mongodb.org/browse/PHPLIB","version":"1.7.0-beta2","version_normalized":"1.7.0.0-beta2","license":["Apache-2.0"],"authors":[{"name":"Andreas Braun","email":"andreas.braun@mongodb.com"},{"name":"Jeremy Mikola","email":"jmikola@gmail.com"},{"name":"Katherine Walker","email":"katherine.walker@mongodb.com"}],"source":{"type":"git","url":"https://github.com/mongodb/mongo-php-library.git","reference":"8ff57584f582594473287dc77e1d84b30039b2e4"},"dist":{"type":"zip","url":"https://api.github.com/repos/mongodb/mongo-php-library/zipball/8ff57584f582594473287dc77e1d84b30039b2e4","reference":"8ff57584f582594473287dc77e1d84b30039b2e4","shasum":""},"type":"library","time":"2020-06-01T20:21:26+00:00","autoload":{"psr-4":{"MongoDB\\":"src/"},"files":["src/functions.php"]},"extra":{"branch-alias":{"dev-master":"1.7.x-dev"}},"require":{"php":"^7.0","ext-hash":"*","ext-json":"*","ext-mongodb":"^1.8","jean85/pretty-package-versions":"^1.2"},"require-dev":{"phpunit/phpunit":"^6.4 || ^8.3","sebastian/comparator":"^2.0 || ^3.0","squizlabs/php_codesniffer":"^3.5, <3.5.5","symfony/phpunit-bridge":"^4.4@dev"},"uid":3939539},"1.7.0-rc1":{"name":"mongodb/mongodb","description":"MongoDB driver library","keywords":["database","persistence","mongodb","driver"],"homepage":"https://jira.mongodb.org/browse/PHPLIB","version":"1.7.0-rc1","version_normalized":"1.7.0.0-RC1","license":["Apache-2.0"],"authors":[{"name":"Andreas Braun","email":"andreas.braun@mongodb.com"},{"name":"Jeremy Mikola","email":"jmikola@gmail.com"}],"source":{"type":"git","url":"https://github.com/mongodb/mongo-php-library.git","reference":"74198006d8bfbdfd52603720ffb500f543725ed6"},"dist":{"type":"zip","url":"https://api.github.com/repos/mongodb/mongo-php-library/zipball/74198006d8bfbdfd52603720ffb500f543725ed6","reference":"74198006d8bfbdfd52603720ffb500f543725ed6","shasum":""},"type":"library","time":"2020-07-17T00:14:39+00:00","autoload":{"psr-4":{"MongoDB\\":"src/"},"files":["src/functions.php"]},"extra":{"branch-alias":{"dev-master":"1.7.x-dev"}},"require":{"php":"^7.0","ext-hash":"*","ext-json":"*","ext-mongodb":"^1.8","jean85/pretty-package-versions":"^1.2"},"require-dev":{"phpunit/phpunit":"^6.4 || ^8.3","sebastian/comparator":"^2.0 || ^3.0","squizlabs/php_codesniffer":"^3.5, <3.5.5","symfony/phpunit-bridge":"^4.4@dev"},"uid":4266054},"1.7.1":{"name":"mongodb/mongodb","description":"MongoDB driver library","keywords":["database","persistence","mongodb","driver"],"homepage":"https://jira.mongodb.org/browse/PHPLIB","version":"1.7.1","version_normalized":"1.7.1.0","license":["Apache-2.0"],"authors":[{"name":"Andreas Braun","email":"andreas.braun@mongodb.com"},{"name":"Jeremy Mikola","email":"jmikola@gmail.com"}],"source":{"type":"git","url":"https://github.com/mongodb/mongo-php-library.git","reference":"b35af66631a11ee730ff1fde295f71e89f01f121"},"dist":{"type":"zip","url":"https://api.github.com/repos/mongodb/mongo-php-library/zipball/b35af66631a11ee730ff1fde295f71e89f01f121","reference":"b35af66631a11ee730ff1fde295f71e89f01f121","shasum":""},"type":"library","time":"2020-09-22T13:26:09+00:00","autoload":{"psr-4":{"MongoDB\\":"src/"},"files":["src/functions.php"]},"extra":{"branch-alias":{"dev-master":"1.7.x-dev"}},"require":{"php":"^7.0","ext-hash":"*","ext-json":"*","ext-mongodb":"^1.8","jean85/pretty-package-versions":"^1.2"},"require-dev":{"phpunit/phpunit":"^6.4 || ^8.3","sebastian/comparator":"^2.0 || ^3.0","squizlabs/php_codesniffer":"^3.5, <3.5.5","symfony/phpunit-bridge":"^4.4@dev"},"uid":4521538},"1.7.2":{"name":"mongodb/mongodb","description":"MongoDB driver library","keywords":["database","persistence","mongodb","driver"],"homepage":"https://jira.mongodb.org/browse/PHPLIB","version":"1.7.2","version_normalized":"1.7.2.0","license":["Apache-2.0"],"authors":[{"name":"Andreas Braun","email":"andreas.braun@mongodb.com"},{"name":"Jeremy Mikola","email":"jmikola@gmail.com"}],"source":{"type":"git","url":"https://github.com/mongodb/mongo-php-library.git","reference":"38b685191c047a57275d6ccd2ea5c50f23638485"},"dist":{"type":"zip","url":"https://api.github.com/repos/mongodb/mongo-php-library/zipball/38b685191c047a57275d6ccd2ea5c50f23638485","reference":"38b685191c047a57275d6ccd2ea5c50f23638485","shasum":""},"type":"library","time":"2020-10-08T10:06:19+00:00","autoload":{"psr-4":{"MongoDB\\":"src/"},"files":["src/functions.php"]},"extra":{"branch-alias":{"dev-master":"1.7.x-dev"}},"require":{"php":"^7.0","ext-hash":"*","ext-json":"*","ext-mongodb":"^1.8","jean85/pretty-package-versions":"^1.2"},"require-dev":{"phpunit/phpunit":"^6.4 || ^8.3","sebastian/comparator":"^2.0 || ^3.0","squizlabs/php_codesniffer":"^3.5, <3.5.5","symfony/phpunit-bridge":"^4.4@dev"},"uid":4619333},"1.8.0":{"name":"mongodb/mongodb","description":"MongoDB driver library","keywords":["database","persistence","mongodb","driver"],"homepage":"https://jira.mongodb.org/browse/PHPLIB","version":"1.8.0","version_normalized":"1.8.0.0","license":["Apache-2.0"],"authors":[{"name":"Andreas Braun","email":"andreas.braun@mongodb.com"},{"name":"Jeremy Mikola","email":"jmikola@gmail.com"}],"source":{"type":"git","url":"https://github.com/mongodb/mongo-php-library.git","reference":"953dbc19443aa9314c44b7217a16873347e6840d"},"dist":{"type":"zip","url":"https://api.github.com/repos/mongodb/mongo-php-library/zipball/953dbc19443aa9314c44b7217a16873347e6840d","reference":"953dbc19443aa9314c44b7217a16873347e6840d","shasum":""},"type":"library","time":"2020-11-25T12:26:02+00:00","autoload":{"psr-4":{"MongoDB\\":"src/"},"files":["src/functions.php"]},"extra":{"branch-alias":{"dev-master":"1.8.x-dev"}},"require":{"php":"^7.0 || ^8.0","ext-hash":"*","ext-json":"*","ext-mongodb":"^1.8.1","jean85/pretty-package-versions":"^1.2","symfony/polyfill-php80":"^1.19"},"require-dev":{"squizlabs/php_codesniffer":"^3.5, <3.5.5","symfony/phpunit-bridge":"5.x-dev"},"uid":4681303},"1.8.0-RC1":{"name":"mongodb/mongodb","description":"MongoDB driver library","keywords":["database","persistence","mongodb","driver"],"homepage":"https://jira.mongodb.org/browse/PHPLIB","version":"1.8.0-RC1","version_normalized":"1.8.0.0-RC1","license":["Apache-2.0"],"authors":[{"name":"Andreas Braun","email":"andreas.braun@mongodb.com"},{"name":"Jeremy Mikola","email":"jmikola@gmail.com"}],"source":{"type":"git","url":"https://github.com/mongodb/mongo-php-library.git","reference":"9d94b85a4f106fb3be15d1bb65e9cd42381fb3da"},"dist":{"type":"zip","url":"https://api.github.com/repos/mongodb/mongo-php-library/zipball/9d94b85a4f106fb3be15d1bb65e9cd42381fb3da","reference":"9d94b85a4f106fb3be15d1bb65e9cd42381fb3da","shasum":""},"type":"library","time":"2020-11-10T21:27:51+00:00","autoload":{"psr-4":{"MongoDB\\":"src/"},"files":["src/functions.php"]},"extra":{"branch-alias":{"dev-master":"1.8.x-dev"}},"require":{"php":"^7.0 || ^8.0","ext-hash":"*","ext-json":"*","ext-mongodb":"^1.8.1","jean85/pretty-package-versions":"^1.2","symfony/polyfill-php80":"^1.19"},"require-dev":{"squizlabs/php_codesniffer":"^3.5, <3.5.5","symfony/phpunit-bridge":"5.x-dev"},"uid":4633291},"1.9.0":{"name":"mongodb/mongodb","description":"MongoDB driver library","keywords":["database","persistence","mongodb","driver"],"homepage":"https://jira.mongodb.org/browse/PHPLIB","version":"1.9.0","version_normalized":"1.9.0.0","license":["Apache-2.0"],"authors":[{"name":"Andreas Braun","email":"andreas.braun@mongodb.com"},{"name":"Jeremy Mikola","email":"jmikola@gmail.com"}],"source":{"type":"git","url":"https://github.com/mongodb/mongo-php-library.git","reference":"4afe9254e87252879bfbb625858e78fbe072daa0"},"dist":{"type":"zip","url":"https://api.github.com/repos/mongodb/mongo-php-library/zipball/4afe9254e87252879bfbb625858e78fbe072daa0","reference":"4afe9254e87252879bfbb625858e78fbe072daa0","shasum":""},"type":"library","time":"2021-07-13T20:03:24+00:00","autoload":{"psr-4":{"MongoDB\\":"src/"},"files":["src/functions.php"]},"extra":{"branch-alias":{"dev-master":"1.9.x-dev"}},"require":{"php":"^7.1 || ^8.0","ext-hash":"*","ext-json":"*","ext-mongodb":"^1.10.0","jean85/pretty-package-versions":"^1.2 || ^2.0.1","symfony/polyfill-php80":"^1.19"},"require-dev":{"squizlabs/php_codesniffer":"^3.6","doctrine/coding-standard":"^9.0","symfony/phpunit-bridge":"^5.2"},"uid":5360565},"1.9.0-alpha1":{"name":"mongodb/mongodb","description":"MongoDB driver library","keywords":["database","persistence","mongodb","driver"],"homepage":"https://jira.mongodb.org/browse/PHPLIB","version":"1.9.0-alpha1","version_normalized":"1.9.0.0-alpha1","license":["Apache-2.0"],"authors":[{"name":"Andreas Braun","email":"andreas.braun@mongodb.com"},{"name":"Jeremy Mikola","email":"jmikola@gmail.com"}],"source":{"type":"git","url":"https://github.com/mongodb/mongo-php-library.git","reference":"8123216f21d31a2a5b845aa91fba7a182d060509"},"dist":{"type":"zip","url":"https://api.github.com/repos/mongodb/mongo-php-library/zipball/8123216f21d31a2a5b845aa91fba7a182d060509","reference":"8123216f21d31a2a5b845aa91fba7a182d060509","shasum":""},"type":"library","time":"2021-04-09T12:02:02+00:00","autoload":{"psr-4":{"MongoDB\\":"src/"},"files":["src/functions.php"]},"extra":{"branch-alias":{"dev-master":"1.9.x-dev"}},"require":{"php":"^7.0 || ^8.0","ext-hash":"*","ext-json":"*","ext-mongodb":"^1.10.0","jean85/pretty-package-versions":"^1.2 || ^2.0.1","symfony/polyfill-php80":"^1.19"},"require-dev":{"squizlabs/php_codesniffer":"^3.5, <3.5.5","symfony/phpunit-bridge":"^5.2"},"uid":5093910},"dev-master":{"name":"mongodb/mongodb","description":"MongoDB driver library","keywords":["database","persistence","mongodb","driver"],"homepage":"https://jira.mongodb.org/browse/PHPLIB","version":"dev-master","version_normalized":"9999999-dev","license":["Apache-2.0"],"authors":[{"name":"Andreas Braun","email":"andreas.braun@mongodb.com"},{"name":"Jeremy Mikola","email":"jmikola@gmail.com"}],"source":{"type":"git","url":"https://github.com/mongodb/mongo-php-library.git","reference":"f4a6e8d84c1650a5bb086597a626edbc7f493fcf"},"dist":{"type":"zip","url":"https://api.github.com/repos/mongodb/mongo-php-library/zipball/f4a6e8d84c1650a5bb086597a626edbc7f493fcf","reference":"f4a6e8d84c1650a5bb086597a626edbc7f493fcf","shasum":""},"type":"library","time":"2021-09-07T06:17:59+00:00","autoload":{"psr-4":{"MongoDB\\":"src/"},"files":["src/functions.php"]},"extra":{"branch-alias":{"dev-master":"1.10.x-dev"}},"default-branch":true,"require":{"ext-hash":"*","ext-json":"*","symfony/polyfill-php80":"^1.19","jean85/pretty-package-versions":"^1.2 || ^2.0.1","php":"^7.1 || ^8.0","ext-mongodb":"^1.11.0"},"require-dev":{"symfony/phpunit-bridge":"^5.2","squizlabs/php_codesniffer":"^3.6","doctrine/coding-standard":"^9.0"},"uid":4146782},"v1.0.x-dev":{"name":"mongodb/mongodb","description":"MongoDB driver library","keywords":["database","persistence","mongodb","driver"],"homepage":"https://jira.mongodb.org/browse/PHPLIB","version":"v1.0.x-dev","version_normalized":"1.0.9999999.9999999-dev","license":["Apache-2.0"],"authors":[{"name":"Jeremy Mikola","email":"jmikola@gmail.com"},{"name":"Hannes Magnusson","email":"bjori@mongodb.com"},{"name":"Derick Rethans","email":"github@derickrethans.nl"}],"source":{"type":"git","url":"https://github.com/mongodb/mongo-php-library.git","reference":"2f99156b29bc85582415d6a32bc31010d61a0a71"},"dist":{"type":"zip","url":"https://api.github.com/repos/mongodb/mongo-php-library/zipball/2f99156b29bc85582415d6a32bc31010d61a0a71","reference":"2f99156b29bc85582415d6a32bc31010d61a0a71","shasum":""},"type":"library","time":"2017-02-16T18:35:09+00:00","autoload":{"psr-4":{"MongoDB\\":"src/"},"files":["src/functions.php"]},"require":{"php":">=5.4","ext-mongodb":"^1.1.0"},"uid":736450},"v1.1.x-dev":{"name":"mongodb/mongodb","description":"MongoDB driver library","keywords":["database","persistence","mongodb","driver"],"homepage":"https://jira.mongodb.org/browse/PHPLIB","version":"v1.1.x-dev","version_normalized":"1.1.9999999.9999999-dev","license":["Apache-2.0"],"authors":[{"name":"Hannes Magnusson","email":"bjori@mongodb.com"},{"name":"Jeremy Mikola","email":"jmikola@gmail.com"},{"name":"Derick Rethans","email":"github@derickrethans.nl"}],"source":{"type":"git","url":"https://github.com/mongodb/mongo-php-library.git","reference":"ce591998fccd7a1b64d4354542f33b14beb0c089"},"dist":{"type":"zip","url":"https://api.github.com/repos/mongodb/mongo-php-library/zipball/ce591998fccd7a1b64d4354542f33b14beb0c089","reference":"ce591998fccd7a1b64d4354542f33b14beb0c089","shasum":""},"type":"library","time":"2021-07-14T15:21:23+00:00","autoload":{"psr-4":{"MongoDB\\":"src/"},"files":["src/functions.php"]},"require":{"php":">=5.4","ext-mongodb":"^1.2.0"},"require-dev":{"phpunit/phpunit":"^4.8"},"uid":1184992},"v1.2.x-dev":{"name":"mongodb/mongodb","description":"MongoDB driver library","keywords":["database","persistence","mongodb","driver"],"homepage":"https://jira.mongodb.org/browse/PHPLIB","version":"v1.2.x-dev","version_normalized":"1.2.9999999.9999999-dev","license":["Apache-2.0"],"authors":[{"name":"Hannes Magnusson","email":"bjori@mongodb.com"},{"name":"Jeremy Mikola","email":"jmikola@gmail.com"},{"name":"Derick Rethans","email":"github@derickrethans.nl"}],"source":{"type":"git","url":"https://github.com/mongodb/mongo-php-library.git","reference":"c4932f913e0c32b1502f8782a3844357317e6bb6"},"dist":{"type":"zip","url":"https://api.github.com/repos/mongodb/mongo-php-library/zipball/c4932f913e0c32b1502f8782a3844357317e6bb6","reference":"c4932f913e0c32b1502f8782a3844357317e6bb6","shasum":""},"type":"library","time":"2021-07-14T15:24:15+00:00","autoload":{"psr-4":{"MongoDB\\":"src/"},"files":["src/functions.php"]},"require":{"php":">=5.5","ext-hash":"*","ext-json":"*","ext-mongodb":"^1.3.0"},"require-dev":{"phpunit/phpunit":"^4.8"},"uid":1691483},"v1.3.x-dev":{"name":"mongodb/mongodb","description":"MongoDB driver library","keywords":["database","persistence","mongodb","driver"],"homepage":"https://jira.mongodb.org/browse/PHPLIB","version":"v1.3.x-dev","version_normalized":"1.3.9999999.9999999-dev","license":["Apache-2.0"],"authors":[{"name":"Jeremy Mikola","email":"jmikola@gmail.com"},{"name":"Derick Rethans","email":"github@derickrethans.nl"},{"name":"Katherine Walker","email":"katherine.walker@mongodb.com"}],"source":{"type":"git","url":"https://github.com/mongodb/mongo-php-library.git","reference":"d28dece803b42f8994fcce6fc093a49565c2a545"},"dist":{"type":"zip","url":"https://api.github.com/repos/mongodb/mongo-php-library/zipball/d28dece803b42f8994fcce6fc093a49565c2a545","reference":"d28dece803b42f8994fcce6fc093a49565c2a545","shasum":""},"type":"library","time":"2021-07-14T15:26:58+00:00","autoload":{"psr-4":{"MongoDB\\":"src/"},"files":["src/functions.php"]},"require":{"php":">=5.5","ext-hash":"*","ext-json":"*","ext-mongodb":"^1.4.0"},"require-dev":{"phpunit/phpunit":"^4.8.36 || ^6.4"},"uid":1945215},"v1.4.x-dev":{"name":"mongodb/mongodb","description":"MongoDB driver library","keywords":["database","persistence","mongodb","driver"],"homepage":"https://jira.mongodb.org/browse/PHPLIB","version":"v1.4.x-dev","version_normalized":"1.4.9999999.9999999-dev","license":["Apache-2.0"],"authors":[{"name":"Jeremy Mikola","email":"jmikola@gmail.com"},{"name":"Derick Rethans","email":"github@derickrethans.nl"},{"name":"Katherine Walker","email":"katherine.walker@mongodb.com"}],"source":{"type":"git","url":"https://github.com/mongodb/mongo-php-library.git","reference":"cda4d9cc54b4148894bce977c01e1c2cba42bd8d"},"dist":{"type":"zip","url":"https://api.github.com/repos/mongodb/mongo-php-library/zipball/cda4d9cc54b4148894bce977c01e1c2cba42bd8d","reference":"cda4d9cc54b4148894bce977c01e1c2cba42bd8d","shasum":""},"type":"library","time":"2021-07-14T15:28:04+00:00","autoload":{"psr-4":{"MongoDB\\":"src/"},"files":["src/functions.php"]},"require":{"php":">=5.5","ext-hash":"*","ext-json":"*","ext-mongodb":"^1.5.0"},"require-dev":{"phpunit/phpunit":"^4.8.36 || ^6.4"},"uid":2551994},"v1.5.x-dev":{"name":"mongodb/mongodb","description":"MongoDB driver library","keywords":["database","persistence","mongodb","driver"],"homepage":"https://jira.mongodb.org/browse/PHPLIB","version":"v1.5.x-dev","version_normalized":"1.5.9999999.9999999-dev","license":["Apache-2.0"],"authors":[{"name":"Andreas Braun","email":"andreas.braun@mongodb.com"},{"name":"Jeremy Mikola","email":"jmikola@gmail.com"},{"name":"Katherine Walker","email":"katherine.walker@mongodb.com"}],"source":{"type":"git","url":"https://github.com/mongodb/mongo-php-library.git","reference":"56e08eeb7d228c8ced6a8e505288555be3bb9466"},"dist":{"type":"zip","url":"https://api.github.com/repos/mongodb/mongo-php-library/zipball/56e08eeb7d228c8ced6a8e505288555be3bb9466","reference":"56e08eeb7d228c8ced6a8e505288555be3bb9466","shasum":""},"type":"library","time":"2021-07-14T15:28:11+00:00","autoload":{"psr-4":{"MongoDB\\":"src/"},"files":["src/functions.php"]},"extra":{"branch-alias":{"dev-master":"1.5.x-dev"}},"require":{"php":"^5.6 || ^7.0","ext-hash":"*","ext-json":"*","ext-mongodb":"^1.6"},"require-dev":{"phpunit/phpunit":"^5.7.27 || ^6.4 || ^8.3","sebastian/comparator":"^1.0 || ^2.0 || ^3.0","squizlabs/php_codesniffer":"^3.4","symfony/phpunit-bridge":"^4.4@dev"},"uid":3221927},"v1.6.x-dev":{"name":"mongodb/mongodb","description":"MongoDB driver library","keywords":["database","persistence","mongodb","driver"],"homepage":"https://jira.mongodb.org/browse/PHPLIB","version":"v1.6.x-dev","version_normalized":"1.6.9999999.9999999-dev","license":["Apache-2.0"],"authors":[{"name":"Andreas Braun","email":"andreas.braun@mongodb.com"},{"name":"Jeremy Mikola","email":"jmikola@gmail.com"},{"name":"Katherine Walker","email":"katherine.walker@mongodb.com"}],"source":{"type":"git","url":"https://github.com/mongodb/mongo-php-library.git","reference":"ec6eaaf06500febd3519d5559ec35044558651b6"},"dist":{"type":"zip","url":"https://api.github.com/repos/mongodb/mongo-php-library/zipball/ec6eaaf06500febd3519d5559ec35044558651b6","reference":"ec6eaaf06500febd3519d5559ec35044558651b6","shasum":""},"type":"library","time":"2021-07-14T15:28:19+00:00","autoload":{"psr-4":{"MongoDB\\":"src/"},"files":["src/functions.php"]},"extra":{"branch-alias":{"dev-master":"1.6.x-dev"}},"require":{"php":"^5.6 || ^7.0","ext-hash":"*","ext-json":"*","ext-mongodb":"^1.7"},"require-dev":{"phpunit/phpunit":"^5.7.27 || ^6.4 || ^8.3","sebastian/comparator":"^1.0 || ^2.0 || ^3.0","squizlabs/php_codesniffer":"^3.4","symfony/phpunit-bridge":"^4.4@dev"},"uid":3586090},"v1.7.x-dev":{"name":"mongodb/mongodb","description":"MongoDB driver library","keywords":["database","persistence","mongodb","driver"],"homepage":"https://jira.mongodb.org/browse/PHPLIB","version":"v1.7.x-dev","version_normalized":"1.7.9999999.9999999-dev","license":["Apache-2.0"],"authors":[{"name":"Andreas Braun","email":"andreas.braun@mongodb.com"},{"name":"Jeremy Mikola","email":"jmikola@gmail.com"}],"source":{"type":"git","url":"https://github.com/mongodb/mongo-php-library.git","reference":"702dacb75e79b7349cb9905eab1dc962231f2dfe"},"dist":{"type":"zip","url":"https://api.github.com/repos/mongodb/mongo-php-library/zipball/702dacb75e79b7349cb9905eab1dc962231f2dfe","reference":"702dacb75e79b7349cb9905eab1dc962231f2dfe","shasum":""},"type":"library","time":"2021-08-30T17:08:06+00:00","autoload":{"psr-4":{"MongoDB\\":"src/"},"files":["src/functions.php"]},"extra":{"branch-alias":{"dev-master":"1.7.x-dev"}},"require":{"php":"^7.0","ext-hash":"*","ext-json":"*","ext-mongodb":"^1.8","jean85/pretty-package-versions":"^1.2"},"require-dev":{"phpunit/phpunit":"^6.4 || ^8.3","sebastian/comparator":"^2.0 || ^3.0","symfony/phpunit-bridge":"^4.4@dev","squizlabs/php_codesniffer":"^3.5, <3.5.5"},"uid":3781848},"v1.8.x-dev":{"name":"mongodb/mongodb","description":"MongoDB driver library","keywords":["database","persistence","mongodb","driver"],"homepage":"https://jira.mongodb.org/browse/PHPLIB","version":"v1.8.x-dev","version_normalized":"1.8.9999999.9999999-dev","license":["Apache-2.0"],"authors":[{"name":"Andreas Braun","email":"andreas.braun@mongodb.com"},{"name":"Jeremy Mikola","email":"jmikola@gmail.com"}],"source":{"type":"git","url":"https://github.com/mongodb/mongo-php-library.git","reference":"143800df805ef984f1d8e02377fe78e2ee0ffac1"},"dist":{"type":"zip","url":"https://api.github.com/repos/mongodb/mongo-php-library/zipball/143800df805ef984f1d8e02377fe78e2ee0ffac1","reference":"143800df805ef984f1d8e02377fe78e2ee0ffac1","shasum":""},"type":"library","time":"2021-08-30T17:10:30+00:00","autoload":{"psr-4":{"MongoDB\\":"src/"},"files":["src/functions.php"]},"extra":{"branch-alias":{"dev-master":"1.8.x-dev"}},"require":{"php":"^7.0 || ^8.0","ext-hash":"*","ext-json":"*","ext-mongodb":"^1.8.1","jean85/pretty-package-versions":"^1.2","symfony/polyfill-php80":"^1.19"},"require-dev":{"squizlabs/php_codesniffer":"^3.5, <3.5.5","symfony/phpunit-bridge":"^5.2"},"uid":4633288},"v1.9.x-dev":{"name":"mongodb/mongodb","description":"MongoDB driver library","keywords":["database","persistence","mongodb","driver"],"homepage":"https://jira.mongodb.org/browse/PHPLIB","version":"v1.9.x-dev","version_normalized":"1.9.9999999.9999999-dev","license":["Apache-2.0"],"authors":[{"name":"Andreas Braun","email":"andreas.braun@mongodb.com"},{"name":"Jeremy Mikola","email":"jmikola@gmail.com"}],"source":{"type":"git","url":"https://github.com/mongodb/mongo-php-library.git","reference":"46a9a8faf7e700aa7bcad06dfb6bfc2c1fad12a5"},"dist":{"type":"zip","url":"https://api.github.com/repos/mongodb/mongo-php-library/zipball/46a9a8faf7e700aa7bcad06dfb6bfc2c1fad12a5","reference":"46a9a8faf7e700aa7bcad06dfb6bfc2c1fad12a5","shasum":""},"type":"library","time":"2021-08-30T17:10:38+00:00","autoload":{"psr-4":{"MongoDB\\":"src/"},"files":["src/functions.php"]},"extra":{"branch-alias":{"dev-master":"1.9.x-dev"}},"require":{"php":"^7.1 || ^8.0","ext-hash":"*","ext-json":"*","ext-mongodb":"^1.10.0","jean85/pretty-package-versions":"^1.2 || ^2.0.1","symfony/polyfill-php80":"^1.19"},"require-dev":{"squizlabs/php_codesniffer":"^3.6","doctrine/coding-standard":"^9.0","symfony/phpunit-bridge":"^5.2"},"uid":5360563}},"raffaelj/cpmultiplane":{"0.2.2":{"name":"raffaelj/cpmultiplane","description":"A small PHP frontend for Cockpit CMS","keywords":["php","frontend","cockpit"],"homepage":"https://github.com/raffaelj/CpMultiplane","version":"0.2.2","version_normalized":"0.2.2.0","license":["MIT"],"authors":[{"name":"Raffael Jesche","homepage":"https://www.rlj.me"}],"source":{"type":"git","url":"https://github.com/raffaelj/CpMultiplane.git","reference":"efb49467cc4d8c7a12fc5a69683f3e30001bcba1"},"dist":{"type":"zip","url":"https://api.github.com/repos/raffaelj/CpMultiplane/zipball/efb49467cc4d8c7a12fc5a69683f3e30001bcba1","reference":"efb49467cc4d8c7a12fc5a69683f3e30001bcba1","shasum":""},"type":"project","time":"2020-10-13T12:45:04+00:00","extra":{"installer-name":"CpMultiplane","installer-types":["project","library"],"installer-paths":{"cockpit":["aheinze/cockpit"],"cockpit/addons/{$name}":["type:cockpit-module"]}},"require":{"php":">= 7.1","ext-json":"*","ext-pdo":"*","oomphinc/composer-installers-extender":"^1.1","aheinze/cockpit":"^0.11.2","raffaelj/cockpit-cpmultiplanegui":"^0.2.2","raffaelj/cockpit-uniqueslugs":"^0.5.4","raffaelj/cockpit-formvalidation":"^0.2.11"},"replace":{"phpmailer/phpmailer":"*","claviska/simpleimage":"*","ksubileau/color-thief-php":"*","league/flysystem":"*","firebase/php-jwt":"*","mongodb/mongodb":"*","erusev/parsedown":"*","erusev/parsedown-extra":"*","maennchen/zipstream-php":"*","colinodell/json5":"*"},"uid":4543244},"0.2.3":{"name":"raffaelj/cpmultiplane","description":"A small PHP frontend for Cockpit CMS","keywords":["php","frontend","cockpit"],"homepage":"https://github.com/raffaelj/CpMultiplane","version":"0.2.3","version_normalized":"0.2.3.0","license":["MIT"],"authors":[{"name":"Raffael Jesche","homepage":"https://www.rlj.me"}],"source":{"type":"git","url":"https://github.com/raffaelj/CpMultiplane.git","reference":"aa3bde9dd39e0d4db1182bc765ac345ab103cd80"},"dist":{"type":"zip","url":"https://api.github.com/repos/raffaelj/CpMultiplane/zipball/aa3bde9dd39e0d4db1182bc765ac345ab103cd80","reference":"aa3bde9dd39e0d4db1182bc765ac345ab103cd80","shasum":""},"type":"project","time":"2020-10-19T13:40:31+00:00","extra":{"installer-name":"CpMultiplane","installer-types":["project","library"],"installer-paths":{"cockpit":["aheinze/cockpit"],"cockpit/addons/{$name}":["type:cockpit-module"]}},"require":{"php":">= 7.1","ext-json":"*","ext-pdo":"*","oomphinc/composer-installers-extender":"^1.1","aheinze/cockpit":"^0.11.2","raffaelj/cockpit-cpmultiplanegui":"^0.2.2","raffaelj/cockpit-uniqueslugs":"^0.5.4","raffaelj/cockpit-formvalidation":"^0.2.11"},"replace":{"phpmailer/phpmailer":"*","claviska/simpleimage":"*","ksubileau/color-thief-php":"*","league/flysystem":"*","firebase/php-jwt":"*","mongodb/mongodb":"*","erusev/parsedown":"*","erusev/parsedown-extra":"*","maennchen/zipstream-php":"*","colinodell/json5":"*"},"uid":4559397},"0.2.4":{"name":"raffaelj/cpmultiplane","description":"A small PHP frontend for Cockpit CMS","keywords":["php","frontend","cockpit"],"homepage":"https://github.com/raffaelj/CpMultiplane","version":"0.2.4","version_normalized":"0.2.4.0","license":["MIT"],"authors":[{"name":"Raffael Jesche","homepage":"https://www.rlj.me"}],"source":{"type":"git","url":"https://github.com/raffaelj/CpMultiplane.git","reference":"ce7ffbf3be34a3995ca53ffd8d946162ec92d1a2"},"dist":{"type":"zip","url":"https://api.github.com/repos/raffaelj/CpMultiplane/zipball/ce7ffbf3be34a3995ca53ffd8d946162ec92d1a2","reference":"ce7ffbf3be34a3995ca53ffd8d946162ec92d1a2","shasum":""},"type":"project","time":"2020-10-19T13:54:52+00:00","extra":{"installer-name":"CpMultiplane","installer-types":["project","library"],"installer-paths":{"cockpit":["aheinze/cockpit"],"cockpit/addons/{$name}":["type:cockpit-module"]}},"require":{"php":">= 7.1","ext-json":"*","ext-pdo":"*","oomphinc/composer-installers-extender":"^1.1","aheinze/cockpit":"^0.11.2","raffaelj/cockpit-cpmultiplanegui":"^0.2.2","raffaelj/cockpit-uniqueslugs":"^0.5.4","raffaelj/cockpit-formvalidation":"^0.2.11"},"replace":{"phpmailer/phpmailer":"*","claviska/simpleimage":"*","ksubileau/color-thief-php":"*","league/flysystem":"*","firebase/php-jwt":"*","mongodb/mongodb":"*","erusev/parsedown":"*","erusev/parsedown-extra":"*","maennchen/zipstream-php":"*","colinodell/json5":"*"},"uid":4559416},"dev-master":{"name":"raffaelj/cpmultiplane","description":"A small PHP frontend for Cockpit CMS","keywords":["php","frontend","cockpit"],"homepage":"https://cpmultiplane.rlj.me","version":"dev-master","version_normalized":"9999999-dev","license":["MIT"],"authors":[{"name":"Raffael Jesche","homepage":"https://www.rlj.me"}],"source":{"type":"git","url":"https://github.com/raffaelj/CpMultiplane.git","reference":"b89557f97e7a25a43dfa3f22db3a98ab7b23c5f7"},"dist":{"type":"zip","url":"https://api.github.com/repos/raffaelj/CpMultiplane/zipball/b89557f97e7a25a43dfa3f22db3a98ab7b23c5f7","reference":"b89557f97e7a25a43dfa3f22db3a98ab7b23c5f7","shasum":""},"type":"project","time":"2021-01-05T12:05:01+00:00","extra":{"installer-name":"CpMultiplane","installer-types":["project","library"],"installer-paths":{"cockpit":["aheinze/cockpit"],"cockpit/addons/{$name}":["type:cockpit-module"]}},"default-branch":true,"require":{"php":">= 7.1","ext-json":"*","ext-pdo":"*","aheinze/cockpit":"^0.11.2","raffaelj/cockpit-cpmultiplanegui":"^0.2.2","raffaelj/cockpit-uniqueslugs":"^0.5.4","raffaelj/cockpit-formvalidation":"^0.2.11","oomphinc/composer-installers-extender":"^2.0"},"replace":{"phpmailer/phpmailer":"*","claviska/simpleimage":"*","ksubileau/color-thief-php":"*","league/flysystem":"*","firebase/php-jwt":"*","mongodb/mongodb":"*","erusev/parsedown":"*","erusev/parsedown-extra":"*","maennchen/zipstream-php":"*","colinodell/json5":"*"},"uid":4342609}}}}